{"status_code":0,"data":{"recommend_list":null,"word_list":[{"word":"我和我的父辈限时免费看","label":3,"hot_value":12683943,"word_cover":{"uri":"tos-cn-p-0015/85624125113c4c369ee6a2030e4f83f8","url_list":["https://p9-sign.douyinpic.com/tos-cn-p-0015/85624125113c4c369ee6a2030e4f83f8~noop.jpeg?x-expires=1643749200&x-signature=7Bo9YflZXkAFp%2F3Wn1I%2Bc1Wilgo%3D&from=3218412987","https://p3-sign.douyinpic.com/tos-cn-p-0015/85624125113c4c369ee6a2030e4f83f8~noop.jpeg?x-expires=1643749200&x-signature=JzPwhTpFEnaGrhjZyCsY6pLVha8%3D&from=3218412987","https://p26-sign.douyinpic.com/tos-cn-p-0015/85624125113c4c369ee6a2030e4f83f8~noop.jpeg?x-expires=1643749200&x-signature=h%2Fd9KNG0Wa%2BMrege6%2Byp21NvQ%2Bg%3D&from=3218412987"]},"group_id":"7012994818394723617","sentence_id":"537383","view_count":66527693,"challenge_id":"","position":1,"event_time":1643682509,"related_words":null,"hotlist_param":"{\"version\":1}","word_sub_board":null,"can_extend_detail":false,"word_type":1,"drift_info":null,"discuss_video_count":0,"article_detail_count":3,"video_count":11,"aweme_infos":null,"sentence_tag":2001},{"word":"外国运动员花式体验冬奥村","event_time":1643683544,"drift_info":null,"word_sub_board":null,"video_count":25,"word_type":1,"view_count":58763159,"aweme_infos":null,"sentence_tag":5000,"challenge_id":"","word_cover":{"uri":"tos-cn-p-0015/4613878a865d44428eeaa108cf6f73b9","url_list":["https://p26-sign.douyinpic.com/tos-cn-p-0015/4613878a865d44428eeaa108cf6f73b9~noop.jpeg?x-expires=1643749200&x-signature=xg7Vn1J0t25xklDx92JbOsO%2BBrM%3D&from=3218412987","https://p9-sign.douyinpic.com/tos-cn-p-0015/4613878a865d44428eeaa108cf6f73b9~noop.jpeg?x-expires=1643749200&x-signature=A81zgMhFtg5%2BV%2FuzFc0jwGjwdHs%3D&from=3218412987","https://p6-sign.douyinpic.com/tos-cn-p-0015/4613878a865d44428eeaa108cf6f73b9~noop.jpeg?x-expires=1643749200&x-signature=eVO4QBIvFys9xwwPO44TA1%2BOiuM%3D&from=3218412987"]},"group_id":"7058419607492777256","related_words":null,"hotlist_param":"{\"version\":1}","label":3,"hot_value":9985779,"position":2,"sentence_id":"537392","discuss_video_count":1},{"word_cover":{"uri":"tos-cn-p-0015/119e321dfcb04c1ab6fcf84aa6391de7","url_list":["https://p6-sign.douyinpic.com/tos-cn-p-0015/119e321dfcb04c1ab6fcf84aa6391de7~noop.jpeg?x-expires=1643749200&x-signature=DeKSTk3ukAstnoShTbNTMEdCj2A%3D&from=3218412987","https://p9-sign.douyinpic.com/tos-cn-p-0015/119e321dfcb04c1ab6fcf84aa6391de7~noop.jpeg?x-expires=1643749200&x-signature=U5ik5Ewlc4Zs7sAjujQ9A%2Bp0slI%3D&from=3218412987","https://p3-sign.douyinpic.com/tos-cn-p-0015/119e321dfcb04c1ab6fcf84aa6391de7~noop.jpeg?x-expires=1643749200&x-signature=eIdsT76zlZVTy%2FBbu4d%2FK%2FQLvLw%3D&from=3218412987"]},"group_id":"6903821935383647499","sentence_id":"536937","view_count":53421898,"word":"北京再相逢","label":3,"challenge_id":"","hotlist_param":"{\"version\":1}","aweme_infos":null,"sentence_tag":5000,"hot_value":9897437,"position":3,"room_count":0,"article_detail_count":9,"event_time":1643605929,"drift_info":null,"discuss_video_count":1,"word_sub_board":null,"video_count":7,"word_type":1,"related_words":null},{"word_cover":{"uri":"tos-cn-p-0015/30ab8e6def934521bcf13ab8ef81ba18","url_list":["https://p9-sign.douyinpic.com/tos-cn-p-0015/30ab8e6def934521bcf13ab8ef81ba18~noop.jpeg?x-expires=1643749200&x-signature=b%2F6irauSFyS4VhS6VXt89EiQcjk%3D&from=3218412987","https://p26-sign.douyinpic.com/tos-cn-p-0015/30ab8e6def934521bcf13ab8ef81ba18~noop.jpeg?x-expires=1643749200&x-signature=Pjhk%2F8s%2FaMlsXQP9YsYkwMgoiU0%3D&from=3218412987","https://p6-sign.douyinpic.com/tos-cn-p-0015/30ab8e6def934521bcf13ab8ef81ba18~noop.jpeg?x-expires=1643749200&x-signature=3zBMsUBCmvEB9%2BAHJLxMvPC9WpA%3D&from=3218412987"]},"group_id":"7058060248527312136","view_count":60882086,"drift_info":null,"hot_value":9830419,"position":4,"video_count":6,"event_time":1643641707,"aweme_infos":null,"sentence_tag":2006,"challenge_id":"","sentence_id":"537253","hotlist_param":"{\"version\":1}","discuss_video_count":0,"word_type":1,"label":3,"can_extend_detail":false,"related_words":null,"word_sub_board":null,"word":"张若昀春晚高马尾错位图"},{"word_type":1,"related_words":null,"sentence_tag":20002,"discuss_video_count":0,"challenge_id":"","sentence_id":"537689","aweme_infos":null,"label":3,"position":5,"video_count":3,"drift_info":null,"hotlist_param":"{\"version\":1}","word_sub_board":null,"word":"这就是人类小精灵吧","hot_value":9800268,"word_cover":{"uri":"tos-cn-p-0015/c4f9c2b904954f84a61b986b4b77f68c","url_list":["https://p26-sign.douyinpic.com/tos-cn-p-0015/c4f9c2b904954f84a61b986b4b77f68c~noop.jpeg?x-expires=1643749200&x-signature=VJO55rFZyPHnTEaxlBRFrryLFWA%3D&from=3218412987","https://p9-sign.douyinpic.com/tos-cn-p-0015/c4f9c2b904954f84a61b986b4b77f68c~noop.jpeg?x-expires=1643749200&x-signature=q%2F%2FrTpoFvQPvnWpGVBq5pccNNec%3D&from=3218412987","https://p3-sign.douyinpic.com/tos-cn-p-0015/c4f9c2b904954f84a61b986b4b77f68c~noop.jpeg?x-expires=1643749200&x-signature=XHDL7vyYjpyf0qkf5bhSCmfZYaY%3D&from=3218412987"]},"group_id":"7058284837697918245","event_time":1643715176,"view_count":53074857},{"label":3,"challenge_id":"","position":6,"word_type":1,"sentence_id":"537716","sentence_tag":5000,"drift_info":null,"discuss_video_count":0,"hot_value":9612647,"word_cover":{"uri":"tos-cn-p-0015/353bcbc168e848b5a445205b6c4f0c66","url_list":["https://p3-sign.douyinpic.com/tos-cn-p-0015/353bcbc168e848b5a445205b6c4f0c66~noop.jpeg?x-expires=1643749200&x-signature=m7NUcUood%2BAoxa9vm7MGdrNsRRQ%3D&from=3218412987","https://p26-sign.douyinpic.com/tos-cn-p-0015/353bcbc168e848b5a445205b6c4f0c66~noop.jpeg?x-expires=1643749200&x-signature=%2BcYYb1l5ZtczXuKQDeDaIiW%2FeTs%3D&from=3218412987","https://p6-sign.douyinpic.com/tos-cn-p-0015/353bcbc168e848b5a445205b6c4f0c66~noop.jpeg?x-expires=1643749200&x-signature=Vy5jDMONqJ609TqmjakTFGFpJaY%3D&from=3218412987"]},"can_extend_detail":false,"room_count":2,"event_time":1643718818,"related_words":null,"article_detail_count":18,"word":"国足1比3负越南无缘世界杯","video_count":12,"view_count":73171150,"group_id":"7058420092099220750","hotlist_param":"{\"version\":1}","aweme_infos":null,"word_sub_board":null},{"label":5,"view_count":61448969,"aweme_infos":null,"sentence_tag":2006,"word_cover":{"uri":"tos-cn-p-0015/4298c98608c247bab15c46fa1ba1aed1","url_list":["https://p9-sign.douyinpic.com/tos-cn-p-0015/4298c98608c247bab15c46fa1ba1aed1~noop.jpeg?x-expires=1643749200&x-signature=iZmfORX%2BhPNBDmJiQu0xSyz3mz0%3D&from=3218412987","https://p3-sign.douyinpic.com/tos-cn-p-0015/4298c98608c247bab15c46fa1ba1aed1~noop.jpeg?x-expires=1643749200&x-signature=pJuoyyYaFB8OztTiSt%2FYoVgYHBY%3D&from=3218412987","https://p26-sign.douyinpic.com/tos-cn-p-0015/4298c98608c247bab15c46fa1ba1aed1~noop.jpeg?x-expires=1643749200&x-signature=dHWMHDj59Rk5eUcR4SgDWtaySOk%3D&from=3218412987"]},"event_time":1643642179,"drift_info":null,"discuss_video_count":1,"article_detail_count":4,"word":"三星堆青铜大面具亮相春晚舞台","challenge_id":"","video_count":9,"group_id":"7058094806300595464","word_type":1,"word_sub_board":null,"hot_value":9102956,"position":7,"sentence_id":"537257","related_words":null,"hotlist_param":"{\"version\":1}"},{"hotlist_param":"{\"version\":1}","discuss_video_count":0,"video_count":176,"sentence_id":"537273","related_words":null,"word_type":1,"drift_info":null,"word_sub_board":[3],"word":"虎年第一条抖音","hot_value":9029460,"position":8,"challenge_id":"","sentence_tag":1001,"event_time":1643644256,"view_count":52612145,"aweme_infos":null,"label":9,"word_cover":{"uri":"tos-cn-p-0015/ae0298dd337243969065336a5526c982_1643645014","url_list":["https://p6-sign.douyinpic.com/tos-cn-p-0015/ae0298dd337243969065336a5526c982_1643645014~noop.jpeg?x-expires=1643749200&x-signature=3mIrFOSlRMFoiDWrEhQexCjKW9g%3D&from=3218412987","https://p9-sign.douyinpic.com/tos-cn-p-0015/ae0298dd337243969065336a5526c982_1643645014~noop.jpeg?x-expires=1643749200&x-signature=yQCl4GKfNgYbqk6v6WfGZfEm3YQ%3D&from=3218412987","https://p3-sign.douyinpic.com/tos-cn-p-0015/ae0298dd337243969065336a5526c982_1643645014~noop.jpeg?x-expires=1643749200&x-signature=FUe5Xrr9pL%2FHkRFXVmKsb0IoU30%3D&from=3218412987"]},"group_id":"7046741111338964258"},{"label":3,"hot_value":8955903,"position":9,"word_type":1,"view_count":22714732,"aweme_infos":null,"discuss_video_count":0,"word":"广东压岁钱得惹哭多少孩子","hotlist_param":"{\"version\":1}","sentence_tag":20002,"word_sub_board":null,"related_words":null,"drift_info":null,"event_time":1643672098,"word_cover":{"url_list":["https://p3-sign.douyinpic.com/tos-cn-p-0015/00707a5fa5654883828924022b3e359f_1643648686~noop.jpeg?x-expires=1643749200&x-signature=IiKL98lCTG4MFH6ctOR0IhFmBZE%3D&from=3218412987","https://p6-sign.douyinpic.com/tos-cn-p-0015/00707a5fa5654883828924022b3e359f_1643648686~noop.jpeg?x-expires=1643749200&x-signature=voH9y2Jq8E7wlgtINdRiljY7BPg%3D&from=3218412987","https://p26-sign.douyinpic.com/tos-cn-p-0015/00707a5fa5654883828924022b3e359f_1643648686~noop.jpeg?x-expires=1643749200&x-signature=ls8zQsGSpjp3infs2Da4J6kEOIo%3D&from=3218412987"],"uri":"tos-cn-p-0015/00707a5fa5654883828924022b3e359f_1643648686"},"video_count":23,"group_id":"7058116603140969758","sentence_id":"537314","challenge_id":""},{"position":10,"group_id":"7058264111465878797","word_type":1,"sentence_id":"537638","aweme_infos":null,"sentence_tag":1001,"word":"孟庆旸青绿腰挑战","challenge_id":"","can_extend_detail":false,"hot_value":8068946,"video_count":27,"view_count":59991972,"drift_info":null,"hotlist_param":"{\"version\":1}","word_sub_board":[3],"word_cover":{"uri":"tos-cn-p-0015/dbfbcf27848e43e7a893e91003883c5a","url_list":["https://p6-sign.douyinpic.com/tos-cn-p-0015/dbfbcf27848e43e7a893e91003883c5a~noop.jpeg?x-expires=1643749200&x-signature=Y8D6zyqvZcF54yPtkwVgI%2Bbd6CY%3D&from=3218412987","https://p9-sign.douyinpic.com/tos-cn-p-0015/dbfbcf27848e43e7a893e91003883c5a~noop.jpeg?x-expires=1643749200&x-signature=DxCdQXqTEaKfF2dbKH%2Fj6WCbMt4%3D&from=3218412987","https://p26-sign.douyinpic.com/tos-cn-p-0015/dbfbcf27848e43e7a893e91003883c5a~noop.jpeg?x-expires=1643749200&x-signature=7oLST6Mr3mCLP3pIYHargoZuJbE%3D&from=3218412987"]},"related_words":null,"discuss_video_count":0,"label":5,"event_time":1643709521},{"related_words":null,"label":3,"discuss_video_count":0,"word_sub_board":null,"article_detail_count":18,"hot_value":7614729,"video_count":40,"group_id":"6807033380006270212","word_type":1,"sentence_id":"537428","drift_info":null,"hotlist_param":"{\"version\":1}","word":"今生有你大结局","challenge_id":"","word_cover":{"uri":"tos-cn-p-0015/1774b747eac94886a3c0fdfec2fb285c_1643684445","url_list":["https://p26-sign.douyinpic.com/tos-cn-p-0015/1774b747eac94886a3c0fdfec2fb285c_1643684445~noop.jpeg?x-expires=1643749200&x-signature=Ezca5UHtMJ5bwZ26HQ1saxdWRmQ%3D&from=3218412987","https://p9-sign.douyinpic.com/tos-cn-p-0015/1774b747eac94886a3c0fdfec2fb285c_1643684445~noop.jpeg?x-expires=1643749200&x-signature=SUe14KAZboqPSS2TUwjHriskq2I%3D&from=3218412987","https://p3-sign.douyinpic.com/tos-cn-p-0015/1774b747eac94886a3c0fdfec2fb285c_1643684445~noop.jpeg?x-expires=1643749200&x-signature=IS8sIcYOdb%2Bu4hNu24TXWNRQVuo%3D&from=3218412987"]},"position":11,"can_extend_detail":false,"event_time":1643687430,"view_count":55083892,"aweme_infos":null,"sentence_tag":2002},{"position":12,"view_count":49984366,"word":"奇迹笨小孩致歉声明","hot_value":7580585,"can_extend_detail":false,"sentence_id":"537541","discuss_video_count":0,"word_cover":{"uri":"tos-cn-p-0015/afcdc4203e284ad29d2e5f9538a0f159_1643683914","url_list":["https://p26-sign.douyinpic.com/tos-cn-p-0015/afcdc4203e284ad29d2e5f9538a0f159_1643683914~noop.jpeg?x-expires=1643749200&x-signature=1C5QHWCsfXo5nZ%2BlcWsJOkpU12g%3D&from=3218412987","https://p9-sign.douyinpic.com/tos-cn-p-0015/afcdc4203e284ad29d2e5f9538a0f159_1643683914~noop.jpeg?x-expires=1643749200&x-signature=fucJUPs3MsRLpmkJJt3pmr2qt%2Fk%3D&from=3218412987","https://p3-sign.douyinpic.com/tos-cn-p-0015/afcdc4203e284ad29d2e5f9538a0f159_1643683914~noop.jpeg?x-expires=1643749200&x-signature=IgLsYXueXpjiwWYh0texMbk8HR0%3D&from=3218412987"]},"video_count":16,"group_id":"7058234776461825310","related_words":null,"aweme_infos":null,"word_sub_board":null,"article_detail_count":1,"label":3,"challenge_id":"","word_type":1,"event_time":1643698912,"drift_info":null,"hotlist_param":"{\"version\":1}","sentence_tag":2011},{"position":13,"sentence_id":"537467","view_count":43007863,"aweme_infos":null,"discuss_video_count":0,"group_id":"7058215706001397005","word_type":1,"word_sub_board":null,"hot_value":7534765,"word_cover":{"uri":"tos-cn-p-0015/4d1f613ad260439b96410995af3f8665_1643620364","url_list":["https://p26-sign.douyinpic.com/tos-cn-p-0015/4d1f613ad260439b96410995af3f8665_1643620364~noop.jpeg?x-expires=1643749200&x-signature=60bweHtX%2Fhbz%2BCl7KGfCjVDmkLM%3D&from=3218412987","https://p3-sign.douyinpic.com/tos-cn-p-0015/4d1f613ad260439b96410995af3f8665_1643620364~noop.jpeg?x-expires=1643749200&x-signature=x8uXPNMPmioXluHgklUCheHrxJI%3D&from=3218412987","https://p9-sign.douyinpic.com/tos-cn-p-0015/4d1f613ad260439b96410995af3f8665_1643620364~noop.jpeg?x-expires=1643749200&x-signature=k8O2dsED3o43V2cFaIjKnUGpKFA%3D&from=3218412987"]},"video_count":8,"related_words":null,"drift_info":null,"hotlist_param":"{\"version\":1}","sentence_tag":18000,"word":"光明正大顺走宝宝压岁钱","label":3,"challenge_id":"","event_time":1643691875},{"word":"球迷致歉李铁","position":14,"view_count":43923606,"discuss_video_count":0,"can_extend_detail":false,"drift_info":null,"aweme_infos":null,"sentence_tag":5000,"word_sub_board":null,"label":1,"challenge_id":"","word_cover":{"uri":"tos-cn-p-0015/421e5c4d012c4d8487432a3e46516adb_1643724434","url_list":["https://p3-sign.douyinpic.com/tos-cn-p-0015/421e5c4d012c4d8487432a3e46516adb_1643724434~noop.jpeg?x-expires=1643749200&x-signature=8CXNC1KBJYET7jm5uihIWpgC2ak%3D&from=3218412987","https://p6-sign.douyinpic.com/tos-cn-p-0015/421e5c4d012c4d8487432a3e46516adb_1643724434~noop.jpeg?x-expires=1643749200&x-signature=5rhmAPirWcJvzkV93fANJAOn1nE%3D&from=3218412987","https://p26-sign.douyinpic.com/tos-cn-p-0015/421e5c4d012c4d8487432a3e46516adb_1643724434~noop.jpeg?x-expires=1643749200&x-signature=WUqyvckyxkBB8vjz3jNjq%2B4QR8M%3D&from=3218412987"]},"video_count":6,"group_id":"7059072603499861288","sentence_id":"537777","hot_value":7393470,"word_type":1,"event_time":1643726458,"related_words":null,"hotlist_param":"{\"version\":1}"},{"view_count":47866634,"drift_info":null,"discuss_video_count":0,"label":0,"video_count":7,"sentence_id":"537768","event_time":1643725508,"related_words":null,"hot_value":7309505,"group_id":"7058489950589064463","can_extend_detail":false,"word_type":1,"hotlist_param":"{\"version\":1}","challenge_id":"","word_cover":{"uri":"tos-cn-p-0015/353bcbc168e848b5a445205b6c4f0c66","url_list":["https://p26-sign.douyinpic.com/tos-cn-p-0015/353bcbc168e848b5a445205b6c4f0c66~noop.jpeg?x-expires=1643749200&x-signature=%2BcYYb1l5ZtczXuKQDeDaIiW%2FeTs%3D&from=3218412987","https://p9-sign.douyinpic.com/tos-cn-p-0015/353bcbc168e848b5a445205b6c4f0c66~noop.jpeg?x-expires=1643749200&x-signature=x%2Fs7Y0iJICcSuHsn9kl%2BsoeT7oE%3D&from=3218412987","https://p3-sign.douyinpic.com/tos-cn-p-0015/353bcbc168e848b5a445205b6c4f0c66~noop.jpeg?x-expires=1643749200&x-signature=m7NUcUood%2BAoxa9vm7MGdrNsRRQ%3D&from=3218412987"]},"position":15,"aweme_infos":null,"sentence_tag":5000,"word":"现场国足球迷懵了","word_sub_board":null},{"position":16,"video_count":8,"can_extend_detail":false,"event_time":1643633734,"word_cover":{"uri":"tos-cn-p-0015/30811069c9ee4682a668a5003edbed6c_1643633350","url_list":["https://p26-sign.douyinpic.com/tos-cn-p-0015/30811069c9ee4682a668a5003edbed6c_1643633350~noop.jpeg?x-expires=1643749200&x-signature=NI9U3FGcP1VVKsOmhVx3P8j%2BK7U%3D&from=3218412987","https://p9-sign.douyinpic.com/tos-cn-p-0015/30811069c9ee4682a668a5003edbed6c_1643633350~noop.jpeg?x-expires=1643749200&x-signature=nMp3aKwda61SrnYh7cgTW8zYwOk%3D&from=3218412987","https://p3-sign.douyinpic.com/tos-cn-p-0015/30811069c9ee4682a668a5003edbed6c_1643633350~noop.jpeg?x-expires=1643749200&x-signature=CwdMfECg33mjR5EYdHQjPSP39a8%3D&from=3218412987"]},"challenge_id":"","related_words":null,"drift_info":null,"hotlist_param":"{\"version\":1}","word_sub_board":null,"article_detail_count":14,"word":"马凡舒好美","group_id":"6732112377325557003","word_type":1,"sentence_id":"537206","label":3,"view_count":51966009,"aweme_infos":null,"sentence_tag":2006,"discuss_video_count":0,"hot_value":7285795},{"challenge_id":"","video_count":6,"hotlist_param":"{\"version\":1}","sentence_tag":4003,"label":3,"word_cover":{"uri":"tos-cn-o-0004/6f9882ddfe5a4f9b9d72cbaf095ce24a","url_list":["https://p3-sign.douyinpic.com/tos-cn-o-0004/6f9882ddfe5a4f9b9d72cbaf095ce24a~noop.jpeg?x-expires=1643749200&x-signature=mzTVFn6RJ2Xr79oynPAIxSHqdvc%3D&from=3218412987","https://p6-sign.douyinpic.com/tos-cn-o-0004/6f9882ddfe5a4f9b9d72cbaf095ce24a~noop.jpeg?x-expires=1643749200&x-signature=JsSjbAvJKflDbquCW8nVqAM06M0%3D&from=3218412987","https://p26-sign.douyinpic.com/tos-cn-o-0004/6f9882ddfe5a4f9b9d72cbaf095ce24a~noop.jpeg?x-expires=1643749200&x-signature=qm0FDb%2F7edYJNzPQG9%2BdxCd%2BgS8%3D&from=3218412987"]},"word_type":1,"discuss_video_count":1,"aweme_infos":null,"word_sub_board":null,"hot_value":7069737,"group_id":"7057975305399637279","sentence_id":"537137","related_words":null,"view_count":42942754,"drift_info":null,"word":"麦小登和男友的第一个团圆年","position":17,"can_extend_detail":false,"event_time":1643627372},{"video_count":3,"hotlist_param":"{\"version\":1}","aweme_infos":null,"word":"春晚易烊千玺后遗症","word_cover":{"uri":"tos-cn-p-0015/991574e583ed41c390f3e2b8e877f8ec","url_list":["https://p26-sign.douyinpic.com/tos-cn-p-0015/991574e583ed41c390f3e2b8e877f8ec~noop.jpeg?x-expires=1643749200&x-signature=btPcQe86PV1W9y7s2HrCbbuWDTA%3D&from=3218412987","https://p3-sign.douyinpic.com/tos-cn-p-0015/991574e583ed41c390f3e2b8e877f8ec~noop.jpeg?x-expires=1643749200&x-signature=JnKIxv7OQ6jJmallHalrWHy7ncM%3D&from=3218412987","https://p6-sign.douyinpic.com/tos-cn-p-0015/991574e583ed41c390f3e2b8e877f8ec~noop.jpeg?x-expires=1643749200&x-signature=w3o8GmKVtG3MbopprhRpTCCcMJ8%3D&from=3218412987"]},"related_words":null,"sentence_tag":20003,"hot_value":7047094,"challenge_id":"","position":18,"word_type":1,"sentence_id":"537714","word_sub_board":null,"discuss_video_count":0,"label":3,"group_id":"7058175162047632670","can_extend_detail":false,"event_time":1643718778,"view_count":47126294,"drift_info":null},{"challenge_id":"","word_cover":{"uri":"tos-cn-p-0015/d99d1616be2d474db4eb984f14f4ca0e_1643632233","url_list":["https://p3-sign.douyinpic.com/tos-cn-p-0015/d99d1616be2d474db4eb984f14f4ca0e_1643632233~noop.jpeg?x-expires=1643749200&x-signature=2xP%2B0Q6UDgvkh%2BHoYneJIWFRfJU%3D&from=3218412987","https://p9-sign.douyinpic.com/tos-cn-p-0015/d99d1616be2d474db4eb984f14f4ca0e_1643632233~noop.jpeg?x-expires=1643749200&x-signature=q4sJKefwl8KbB%2BrhQXBXqkhdIwg%3D&from=3218412987","https://p26-sign.douyinpic.com/tos-cn-p-0015/d99d1616be2d474db4eb984f14f4ca0e_1643632233~noop.jpeg?x-expires=1643749200&x-signature=7WravnHtRngwsXGZgKEQgRqo2yE%3D&from=3218412987"]},"video_count":7,"group_id":"6958897006974833959","can_extend_detail":false,"word_type":1,"word_sub_board":null,"event_time":1643632991,"view_count":42178567,"hotlist_param":"{\"version\":1}","aweme_infos":null,"sentence_tag":2006,"discuss_video_count":0,"word":"王俊凯王源春晚同框","hot_value":7005664,"position":19,"sentence_id":"537196","related_words":null,"label":1,"drift_info":null,"article_detail_count":2},{"can_extend_detail":false,"sentence_id":"537744","sentence_tag":2003,"word_cover":{"url_list":["https://p3-sign.douyinpic.com/tos-cn-p-0015/62d55c2486bb4368bb7844a8465d5ebe_1643701611~noop.jpeg?x-expires=1643749200&x-signature=EtMU9wta0kBUfNCMI0ldT4J49kU%3D&from=3218412987","https://p9-sign.douyinpic.com/tos-cn-p-0015/62d55c2486bb4368bb7844a8465d5ebe_1643701611~noop.jpeg?x-expires=1643749200&x-signature=gW11W6EWGHIpu8KrIkILvPsMPgw%3D&from=3218412987","https://p26-sign.douyinpic.com/tos-cn-p-0015/62d55c2486bb4368bb7844a8465d5ebe_1643701611~noop.jpeg?x-expires=1643749200&x-signature=Y%2FZSvLx4yzVOJZ%2Fuxm%2BGSVJI9KY%3D&from=3218412987"],"uri":"tos-cn-p-0015/62d55c2486bb4368bb7844a8465d5ebe_1643701611"},"video_count":2,"position":20,"drift_info":null,"hotlist_param":"{\"version\":1}","aweme_infos":null,"word":"谢娜给何炅准备栀子花开惊喜","label":0,"discuss_video_count":0,"word_sub_board":null,"related_words":null,"view_count":38448834,"group_id":"7059530525590115623","word_type":1,"event_time":1643722430,"hot_value":6961451,"challenge_id":""},{"word":"范志毅预言神了","label":0,"challenge_id":"","word_cover":{"uri":"tos-cn-p-0015/bfaf495227a34821a107ec4b3c6259fd_1643721665","url_list":["https://p3-sign.douyinpic.com/tos-cn-p-0015/bfaf495227a34821a107ec4b3c6259fd_1643721665~noop.jpeg?x-expires=1643749200&x-signature=dOugSOE9RSIUN%2FU5vpoxSN5PZSI%3D&from=3218412987","https://p9-sign.douyinpic.com/tos-cn-p-0015/bfaf495227a34821a107ec4b3c6259fd_1643721665~noop.jpeg?x-expires=1643749200&x-signature=Y5reEEyt3kWhZw6J9XWtXlhyDPk%3D&from=3218412987","https://p6-sign.douyinpic.com/tos-cn-p-0015/bfaf495227a34821a107ec4b3c6259fd_1643721665~noop.jpeg?x-expires=1643749200&x-signature=VBUyl5IdLKkd8%2BzgzT74MdYTllU%3D&from=3218412987"]},"position":21,"drift_info":null,"word_sub_board":null,"article_detail_count":13,"group_id":"7058362436139816205","word_type":1,"related_words":null,"view_count":35649576,"aweme_infos":null,"discuss_video_count":0,"sentence_id":"537736","hotlist_param":"{\"version\":1}","hot_value":6944002,"video_count":6,"can_extend_detail":false,"event_time":1643721344,"sentence_tag":5000},{"hot_value":6785703,"challenge_id":"","video_count":18,"event_time":1643612426,"hotlist_param":"{\"version\":1}","discuss_video_count":1,"word_sub_board":null,"word_type":1,"drift_info":null,"aweme_infos":null,"sentence_tag":2001,"label":3,"word_cover":{"uri":"tos-cn-p-0015/344b5032b9744462aea7a1576a4a69dd_1643602637","url_list":["https://p26-sign.douyinpic.com/tos-cn-p-0015/344b5032b9744462aea7a1576a4a69dd_1643602637~noop.jpeg?x-expires=1643749200&x-signature=6M1WbWX2oWh%2BbPo2uKbhy8vU2oc%3D&from=3218412987","https://p6-sign.douyinpic.com/tos-cn-p-0015/344b5032b9744462aea7a1576a4a69dd_1643602637~noop.jpeg?x-expires=1643749200&x-signature=OqxXDDZRMrZAz3XGQmD10Uu%2BBQE%3D&from=3218412987","https://p3-sign.douyinpic.com/tos-cn-p-0015/344b5032b9744462aea7a1576a4a69dd_1643602637~noop.jpeg?x-expires=1643749200&x-signature=TzIOES8cLeMuyit19FbcDdvrJ5I%3D&from=3218412987"]},"position":22,"group_id":"7057885855742973220","related_words":null,"view_count":42266481,"word":"长津湖之水门桥细节满满","can_extend_detail":false,"sentence_id":"536990"},{"word_type":1,"view_count":32732295,"label":0,"position":23,"sentence_id":"536865","aweme_infos":null,"sentence_tag":5000,"word":"CC送谷爱凌定制饺子手机壳","hot_value":6719305,"related_words":null,"discuss_video_count":0,"video_count":5,"group_id":"7058097867999237380","can_extend_detail":false,"event_time":1643598911,"drift_info":null,"hotlist_param":"{\"version\":1}","word_sub_board":null,"challenge_id":"","word_cover":{"uri":"tos-cn-p-0015/cca282894297492b939a5e5df333f5b8_1643597198","url_list":["https://p9-sign.douyinpic.com/tos-cn-p-0015/cca282894297492b939a5e5df333f5b8_1643597198~noop.jpeg?x-expires=1643749200&x-signature=qaVUSkR%2Fbzf5YZpgYW8MWoHw%2FDQ%3D&from=3218412987","https://p26-sign.douyinpic.com/tos-cn-p-0015/cca282894297492b939a5e5df333f5b8_1643597198~noop.jpeg?x-expires=1643749200&x-signature=2BJ7fPrl3ytnoC2IjVn3jLZYYSc%3D&from=3218412987","https://p3-sign.douyinpic.com/tos-cn-p-0015/cca282894297492b939a5e5df333f5b8_1643597198~noop.jpeg?x-expires=1643749200&x-signature=Tv3I%2F7xVWxzNPsrUW5CB8Ax0fJg%3D&from=3218412987"]}},{"word_cover":{"uri":"tos-cn-p-0015/10a746326ddf45e79aaa847e95c5dabe","url_list":["https://p3-sign.douyinpic.com/tos-cn-p-0015/10a746326ddf45e79aaa847e95c5dabe~noop.jpeg?x-expires=1643749200&x-signature=F6dQT%2BTzZjyFmXIUrA%2FTOZ5ZZds%3D&from=3218412987","https://p9-sign.douyinpic.com/tos-cn-p-0015/10a746326ddf45e79aaa847e95c5dabe~noop.jpeg?x-expires=1643749200&x-signature=Y972oNPoLB4kmLgl4fWSbBbB%2Faw%3D&from=3218412987","https://p26-sign.douyinpic.com/tos-cn-p-0015/10a746326ddf45e79aaa847e95c5dabe~noop.jpeg?x-expires=1643749200&x-signature=gvnzZyjppZWMFDGsryiuoPOkCuw%3D&from=3218412987"]},"position":24,"label":3,"challenge_id":"","can_extend_detail":false,"word_type":1,"related_words":null,"hotlist_param":"{\"version\":1}","hot_value":6714509,"event_time":1643708294,"view_count":34465482,"drift_info":null,"aweme_infos":null,"sentence_tag":2003,"discuss_video_count":0,"video_count":5,"group_id":"7059162995302061350","sentence_id":"537622","word_sub_board":null,"word":"井柏然说对谢娜跳女团舞没印象"},{"word_cover":{"uri":"tos-cn-p-0015/7fb3b3abf86c4c44b89bbdac34fc2d74","url_list":["https://p9-sign.douyinpic.com/tos-cn-p-0015/7fb3b3abf86c4c44b89bbdac34fc2d74~noop.jpeg?x-expires=1643749200&x-signature=pzX4ZlfzKfsQpJWE7yqCFX0YZqs%3D&from=3218412987","https://p26-sign.douyinpic.com/tos-cn-p-0015/7fb3b3abf86c4c44b89bbdac34fc2d74~noop.jpeg?x-expires=1643749200&x-signature=v5v07jLVkDBtSKRwe8mk5Pw6MqU%3D&from=3218412987","https://p3-sign.douyinpic.com/tos-cn-p-0015/7fb3b3abf86c4c44b89bbdac34fc2d74~noop.jpeg?x-expires=1643749200&x-signature=8duzenQnPrYDbhED%2Fp%2FK%2BDTIAu8%3D&from=3218412987"]},"position":25,"can_extend_detail":false,"related_words":null,"view_count":32695989,"word":"国足主帅李霄鹏道歉","label":1,"sentence_id":"537785","event_time":1643727401,"sentence_tag":4003,"word_sub_board":null,"hot_value":6706195,"challenge_id":"","video_count":7,"word_type":1,"drift_info":null,"hotlist_param":"{\"version\":1}","discuss_video_count":0,"group_id":"7056773257538245901","aweme_infos":null},{"event_time":1643725641,"word":"范志毅谈中国足球未来","hot_value":6676722,"aweme_infos":null,"sentence_tag":5000,"can_extend_detail":false,"sentence_id":"537770","drift_info":null,"word_sub_board":null,"challenge_id":"","position":26,"video_count":4,"group_id":"6861989536080073992","word_type":1,"related_words":null,"view_count":33143891,"hotlist_param":"{\"version\":1}","label":5,"word_cover":{"uri":"tos-cn-p-0015/e77b20e4bebf46c3bf58ffc72db6d49d","url_list":["https://p3-sign.douyinpic.com/tos-cn-p-0015/e77b20e4bebf46c3bf58ffc72db6d49d~noop.jpeg?x-expires=1643749200&x-signature=FM%2BKMHGDEGtCr%2BgWLQTflBYhSYc%3D&from=3218412987","https://p9-sign.douyinpic.com/tos-cn-p-0015/e77b20e4bebf46c3bf58ffc72db6d49d~noop.jpeg?x-expires=1643749200&x-signature=NEP0M%2FvLsawckzsVqcMShBrHXXM%3D&from=3218412987","https://p26-sign.douyinpic.com/tos-cn-p-0015/e77b20e4bebf46c3bf58ffc72db6d49d~noop.jpeg?x-expires=1643749200&x-signature=WU9sGWcl%2BH706otysDM861P6grc%3D&from=3218412987"]},"discuss_video_count":0},{"aweme_infos":null,"drift_info":null,"word_sub_board":null,"label":3,"word_type":1,"word_cover":{"uri":"tos-cn-p-0015/aec5dc2bf7c541fea7e9bee7dbbd5f9d_1643636409","url_list":["https://p6-sign.douyinpic.com/tos-cn-p-0015/aec5dc2bf7c541fea7e9bee7dbbd5f9d_1643636409~noop.jpeg?x-expires=1643749200&x-signature=CRVGsu1nYjduam5Lb9eeIyRjhkk%3D&from=3218412987","https://p9-sign.douyinpic.com/tos-cn-p-0015/aec5dc2bf7c541fea7e9bee7dbbd5f9d_1643636409~noop.jpeg?x-expires=1643749200&x-signature=KmgrLFEBPcMfI6SWiBGv1%2FS1Apw%3D&from=3218412987","https://p3-sign.douyinpic.com/tos-cn-p-0015/aec5dc2bf7c541fea7e9bee7dbbd5f9d_1643636409~noop.jpeg?x-expires=1643749200&x-signature=Znl8TaelYowSNJ1zhEeTh8PGtuo%3D&from=3218412987"]},"group_id":"7056820945726199074","sentence_id":"537312","view_count":33030098,"hotlist_param":"{\"version\":1}","sentence_tag":20002,"word":"拜年还得看山东人","hot_value":6655790,"video_count":50,"event_time":1643671842,"related_words":null,"discuss_video_count":0,"challenge_id":"","position":27},{"event_time":1643714286,"view_count":28659812,"discuss_video_count":0,"word_sub_board":null,"word":"文艺中国新春特别节目","challenge_id":"","word_cover":{"uri":"tos-cn-p-0015/b4bc8686fe374bce81a964b9e0bc50a5","url_list":["https://p26-sign.douyinpic.com/tos-cn-p-0015/b4bc8686fe374bce81a964b9e0bc50a5~noop.jpeg?x-expires=1643749200&x-signature=iYFBKe8XcVf%2F26%2BQPtuVhzxiQaM%3D&from=3218412987","https://p3-sign.douyinpic.com/tos-cn-p-0015/b4bc8686fe374bce81a964b9e0bc50a5~noop.jpeg?x-expires=1643749200&x-signature=JAumN2omwhhcQ778PbexUnTcWRY%3D&from=3218412987","https://p6-sign.douyinpic.com/tos-cn-p-0015/b4bc8686fe374bce81a964b9e0bc50a5~noop.jpeg?x-expires=1643749200&x-signature=Z5%2B11UVq7t3JdEDBjpr9U1XBGjA%3D&from=3218412987"]},"word_type":1,"related_words":null,"drift_info":null,"aweme_infos":null,"article_detail_count":1,"label":3,"hot_value":6614686,"video_count":7,"group_id":"7057459358855386407","room_count":0,"sentence_tag":2006,"position":28,"sentence_id":"537681","hotlist_param":"{\"version\":1}"},{"hot_value":6530705,"word_cover":{"uri":"tos-cn-p-0015/c7b69d088b144819a358e879908bd260","url_list":["https://p3-sign.douyinpic.com/tos-cn-p-0015/c7b69d088b144819a358e879908bd260~noop.jpeg?x-expires=1643749200&x-signature=uBDi1aPwBl6vIP%2BYufPWmajVbn0%3D&from=3218412987","https://p6-sign.douyinpic.com/tos-cn-p-0015/c7b69d088b144819a358e879908bd260~noop.jpeg?x-expires=1643749200&x-signature=xBuNphOYMx1XiZu0Q1QlcG2tP58%3D&from=3218412987","https://p9-sign.douyinpic.com/tos-cn-p-0015/c7b69d088b144819a358e879908bd260~noop.jpeg?x-expires=1643749200&x-signature=u2SIuJCDJtlowNwAPVbI2qz%2F3HI%3D&from=3218412987"]},"sentence_tag":2006,"discuss_video_count":0,"hotlist_param":"{\"version\":1}","video_count":15,"group_id":"6721647991238694152","sentence_id":"537143","drift_info":null,"event_time":1643627797,"view_count":33221065,"aweme_infos":null,"article_detail_count":12,"word":"央视虎年春晚","challenge_id":"","position":29,"word_type":1,"label":3,"room_count":0,"related_words":null,"word_sub_board":null},{"sentence_id":"537650","event_time":1643710776,"aweme_infos":null,"sentence_tag":3002,"hot_value":6528612,"challenge_id":"","position":30,"word_type":1,"related_words":null,"article_detail_count":12,"word":"中方回应日本众议院通过涉华决议","word_cover":{"uri":"tos-cn-p-0015/d223d8c6f6df4c29abffd3d8ddf09300","url_list":["https://p3-sign.douyinpic.com/tos-cn-p-0015/d223d8c6f6df4c29abffd3d8ddf09300~noop.jpeg?x-expires=1643749200&x-signature=FBSI0anXyJVo1tjCRWn0BF7WLNw%3D&from=3218412987","https://p26-sign.douyinpic.com/tos-cn-p-0015/d223d8c6f6df4c29abffd3d8ddf09300~noop.jpeg?x-expires=1643749200&x-signature=ng92gHIF5DzhefZlQ087wUw%2FDRQ%3D&from=3218412987","https://p6-sign.douyinpic.com/tos-cn-p-0015/d223d8c6f6df4c29abffd3d8ddf09300~noop.jpeg?x-expires=1643749200&x-signature=oZRCX5r9Hn9%2Fod2Q4zbdAGUm%2B04%3D&from=3218412987"]},"video_count":3,"drift_info":null,"discuss_video_count":0,"word_sub_board":null,"label":3,"group_id":"7058541511558665504","view_count":27897755,"hotlist_param":"{\"version\":1}"},{"event_time":1643644241,"related_words":null,"aweme_infos":null,"word":"湖南农村除夕夜有多欢乐","position":31,"word_type":1,"sentence_id":"537272","word_sub_board":null,"view_count":12911189,"drift_info":null,"hotlist_param":"{\"version\":1}","discuss_video_count":1,"label":1,"hot_value":6524611,"word_cover":{"uri":"tos-cn-p-0015/c043cdc3f17849f785baff575329cd43","url_list":["https://p26-sign.douyinpic.com/tos-cn-p-0015/c043cdc3f17849f785baff575329cd43~noop.jpeg?x-expires=1643749200&x-signature=Q6bafaaYWCPNa8yFEwJCdVWw1vY%3D&from=3218412987","https://p9-sign.douyinpic.com/tos-cn-p-0015/c043cdc3f17849f785baff575329cd43~noop.jpeg?x-expires=1643749200&x-signature=ScRtbP4sp%2BfFid847A5wio8jWqU%3D&from=3218412987","https://p3-sign.douyinpic.com/tos-cn-p-0015/c043cdc3f17849f785baff575329cd43~noop.jpeg?x-expires=1643749200&x-signature=5XQ9aJYSEmBy5%2BsHjvzXLHqVvO4%3D&from=3218412987"]},"sentence_tag":20002,"challenge_id":"","video_count":7,"group_id":"7058099016571114759"},{"word_cover":{"uri":"tos-cn-p-0015/2a68446664fd425f8f59671d18ebd6d3","url_list":["https://p3-sign.douyinpic.com/tos-cn-p-0015/2a68446664fd425f8f59671d18ebd6d3~noop.jpeg?x-expires=1643749200&x-signature=WzhJMmdFW75YSrB77TonsIIEX0U%3D&from=3218412987","https://p26-sign.douyinpic.com/tos-cn-p-0015/2a68446664fd425f8f59671d18ebd6d3~noop.jpeg?x-expires=1643749200&x-signature=KF4kfrIvYAtHo%2FXuq%2FejlqPtucc%3D&from=3218412987","https://p6-sign.douyinpic.com/tos-cn-p-0015/2a68446664fd425f8f59671d18ebd6d3~noop.jpeg?x-expires=1643749200&x-signature=eF8ev1jFd1sXaNUVxVB9Fe0InRs%3D&from=3218412987"]},"word_type":1,"sentence_id":"537153","view_count":18859244,"aweme_infos":null,"hot_value":6485579,"challenge_id":"","related_words":null,"hotlist_param":"{\"version\":1}","word":"小鱼海棠和心中最帅的人合拍","group_id":"7057994665387824398","can_extend_detail":false,"sentence_tag":20002,"discuss_video_count":1,"label":3,"position":32,"video_count":4,"event_time":1643628476,"drift_info":null,"word_sub_board":null},{"sentence_id":"537219","view_count":22700043,"hotlist_param":"{\"version\":1}","aweme_infos":null,"word_cover":{"uri":"tos-cn-p-0015/4cf2ac1dc7f54b8d8e3b06a6675da36a_1643638270","url_list":["https://p9-sign.douyinpic.com/tos-cn-p-0015/4cf2ac1dc7f54b8d8e3b06a6675da36a_1643638270~noop.jpeg?x-expires=1643749200&x-signature=9jRAy535XO2DYCnIoxGAWfkX7WA%3D&from=3218412987","https://p3-sign.douyinpic.com/tos-cn-p-0015/4cf2ac1dc7f54b8d8e3b06a6675da36a_1643638270~noop.jpeg?x-expires=1643749200&x-signature=LllwFodCHxNj0VPdRUjtFbAnAcE%3D&from=3218412987","https://p26-sign.douyinpic.com/tos-cn-p-0015/4cf2ac1dc7f54b8d8e3b06a6675da36a_1643638270~noop.jpeg?x-expires=1643749200&x-signature=iLad9EG3MB41MjE%2Bepkiupo6UAY%3D&from=3218412987"]},"video_count":9,"group_id":"7057758502203135240","word_sub_board":null,"word":"贾玲张小斐小品喜上加喜","hot_value":6381478,"sentence_tag":2006,"drift_info":null,"discuss_video_count":1,"label":3,"event_time":1643635722,"related_words":null,"article_detail_count":5,"challenge_id":"","position":33,"word_type":1},{"position":34,"word_type":1,"event_time":1643674982,"sentence_tag":2006,"discuss_video_count":0,"word_sub_board":null,"hot_value":6360973,"challenge_id":"","word_cover":{"url_list":["https://p3-sign.douyinpic.com/tos-cn-p-0015/2937e2ef68e9406b9ccd66101179ad3e~noop.jpeg?x-expires=1643749200&x-signature=WJBcHuS625T3sfF%2BJlSAoO42jwA%3D&from=3218412987","https://p9-sign.douyinpic.com/tos-cn-p-0015/2937e2ef68e9406b9ccd66101179ad3e~noop.jpeg?x-expires=1643749200&x-signature=iubiFPuSxH8coUtSLqXPKs1jeOw%3D&from=3218412987","https://p26-sign.douyinpic.com/tos-cn-p-0015/2937e2ef68e9406b9ccd66101179ad3e~noop.jpeg?x-expires=1643749200&x-signature=D0ssI1cB0F4lBPMwW3Z%2BAs9hu1s%3D&from=3218412987"],"uri":"tos-cn-p-0015/2937e2ef68e9406b9ccd66101179ad3e"},"group_id":"7058073483222373669","sentence_id":"537329","related_words":null,"view_count":24154946,"word":"贾玲给张小斐准备的年夜饭有多绝","video_count":6,"aweme_infos":null,"label":3,"can_extend_detail":false,"drift_info":null,"hotlist_param":"{\"version\":1}"},{"event_time":1643708883,"view_count":16681226,"discuss_video_count":0,"hot_value":6286370,"challenge_id":"","hotlist_param":"{\"version\":1}","word":"湖南卫视华人春晚","position":35,"video_count":21,"word_type":1,"sentence_id":"537630","related_words":null,"word_sub_board":null,"article_detail_count":10,"label":3,"word_cover":{"uri":"tos-cn-p-0015/f8e25a3295754a81a56a655a788e9afe_1643519452","url_list":["https://p26-sign.douyinpic.com/tos-cn-p-0015/f8e25a3295754a81a56a655a788e9afe_1643519452~noop.jpeg?x-expires=1643749200&x-signature=9L0MDQiIN4iqEDtcE7eWHmN4joE%3D&from=3218412987","https://p9-sign.douyinpic.com/tos-cn-p-0015/f8e25a3295754a81a56a655a788e9afe_1643519452~noop.jpeg?x-expires=1643749200&x-signature=LsFX%2B6DI8mIu0aH4qTysCK%2FtVD4%3D&from=3218412987","https://p6-sign.douyinpic.com/tos-cn-p-0015/f8e25a3295754a81a56a655a788e9afe_1643519452~noop.jpeg?x-expires=1643749200&x-signature=CvQQvZQWc8pZ7dC3svJO17g5g58%3D&from=3218412987"]},"group_id":"6579553784924476680","drift_info":null,"aweme_infos":null,"sentence_tag":2006},{"word":"邓超像春晚选中的幸运观众","hot_value":6262979,"related_words":null,"drift_info":null,"label":5,"challenge_id":"","word_cover":{"uri":"tos-cn-p-0015/3307da213b0c4be68a5b6b6e3438a846_1643713920","url_list":["https://p26-sign.douyinpic.com/tos-cn-p-0015/3307da213b0c4be68a5b6b6e3438a846_1643713920~noop.jpeg?x-expires=1643749200&x-signature=uM%2BwtO%2BBazLUQehFsqLHhMsMvN4%3D&from=3218412987","https://p9-sign.douyinpic.com/tos-cn-p-0015/3307da213b0c4be68a5b6b6e3438a846_1643713920~noop.jpeg?x-expires=1643749200&x-signature=Ngn0sUqCoHVYh7qdM4QVXS8vxN4%3D&from=3218412987","https://p3-sign.douyinpic.com/tos-cn-p-0015/3307da213b0c4be68a5b6b6e3438a846_1643713920~noop.jpeg?x-expires=1643749200&x-signature=kmfqeRDTUr7E8NSvWExN%2Bk9N1RI%3D&from=3218412987"]},"word_type":1,"group_id":"7058061367743354143","can_extend_detail":false,"event_time":1643698365,"view_count":18616781,"word_sub_board":null,"article_detail_count":4,"discuss_video_count":0,"position":36,"video_count":11,"sentence_id":"537538","hotlist_param":"{\"version\":1}","aweme_infos":null,"sentence_tag":2006},{"hotlist_param":"{\"version\":1}","word":"没想到张同学这么会写对联","position":37,"word_type":1,"drift_info":null,"sentence_tag":20002,"discuss_video_count":0,"word_sub_board":null,"group_id":"7058085364020368681","can_extend_detail":false,"event_time":1643626525,"view_count":17335324,"label":3,"related_words":null,"aweme_infos":null,"sentence_id":"537130","hot_value":6240763,"challenge_id":"","word_cover":{"uri":"tos-cn-p-0015/7c44a0b973e34ce7b306de67983d9dbc_1643623243","url_list":["https://p3-sign.douyinpic.com/tos-cn-p-0015/7c44a0b973e34ce7b306de67983d9dbc_1643623243~noop.jpeg?x-expires=1643749200&x-signature=1rBSwWftRse8VxmqVNoic8JYsdQ%3D&from=3218412987","https://p9-sign.douyinpic.com/tos-cn-p-0015/7c44a0b973e34ce7b306de67983d9dbc_1643623243~noop.jpeg?x-expires=1643749200&x-signature=ui%2FTWEV3XFO6wsjlzCl6krpEKBg%3D&from=3218412987","https://p26-sign.douyinpic.com/tos-cn-p-0015/7c44a0b973e34ce7b306de67983d9dbc_1643623243~noop.jpeg?x-expires=1643749200&x-signature=sfMSa9TZRZuzX9YFzJ%2FN4bq29mc%3D&from=3218412987"]},"video_count":5},{"label":1,"challenge_id":"","related_words":null,"position":38,"discuss_video_count":0,"view_count":8511578,"sentence_tag":20002,"word":"福建人住的不是别墅是城堡吧","hot_value":6238114,"word_cover":{"uri":"tos-cn-p-0015/024b7b7fc0f34a848ff69e5e23754d8e","url_list":["https://p26-sign.douyinpic.com/tos-cn-p-0015/024b7b7fc0f34a848ff69e5e23754d8e~noop.jpeg?x-expires=1643749200&x-signature=PfdMYBtPs42eIIQh3LTA2zhZfhI%3D&from=3218412987","https://p3-sign.douyinpic.com/tos-cn-p-0015/024b7b7fc0f34a848ff69e5e23754d8e~noop.jpeg?x-expires=1643749200&x-signature=jKAc7byqow6JcqW7yJNJWWMXEVA%3D&from=3218412987","https://p9-sign.douyinpic.com/tos-cn-p-0015/024b7b7fc0f34a848ff69e5e23754d8e~noop.jpeg?x-expires=1643749200&x-signature=dXjxqydVl9H95PUnxxYW%2FJNziYc%3D&from=3218412987"]},"sentence_id":"537250","event_time":1643640676,"drift_info":null,"hotlist_param":"{\"version\":1}","aweme_infos":null,"video_count":6,"group_id":"7058088072412927269","word_type":1,"word_sub_board":null},{"word":"电影四海好笑又好哭","label":5,"group_id":"7057782175663805710","drift_info":null,"aweme_infos":null,"discuss_video_count":0,"word_cover":{"uri":"tos-cn-p-0015/6da87842e2f24e4c8ff99ebdaa9821f6_1643688761","url_list":["https://p6-sign.douyinpic.com/tos-cn-p-0015/6da87842e2f24e4c8ff99ebdaa9821f6_1643688761~noop.jpeg?x-expires=1643749200&x-signature=I%2BlqXuKNhL3Ps3u6G6fTE8wN6a8%3D&from=3218412987","https://p3-sign.douyinpic.com/tos-cn-p-0015/6da87842e2f24e4c8ff99ebdaa9821f6_1643688761~noop.jpeg?x-expires=1643749200&x-signature=XyXAJsMeycgtMlTzQxqBkDibhzs%3D&from=3218412987","https://p9-sign.douyinpic.com/tos-cn-p-0015/6da87842e2f24e4c8ff99ebdaa9821f6_1643688761~noop.jpeg?x-expires=1643749200&x-signature=zZwPs88KxJ%2BcbiG%2Bqk5F49lOpL4%3D&from=3218412987"]},"position":39,"word_type":1,"event_time":1643720520,"view_count":13258391,"sentence_tag":2001,"challenge_id":"","can_extend_detail":false,"sentence_id":"537728","related_words":null,"hotlist_param":"{\"version\":1}","hot_value":6237121,"video_count":16,"word_sub_board":null,"article_detail_count":7},{"aweme_infos":null,"discuss_video_count":0,"position":40,"group_id":"7058396375490762020","related_words":null,"view_count":10677561,"sentence_id":"537735","hot_value":6211979,"challenge_id":"","word_cover":{"uri":"tos-cn-p-0015/fed0bc0035844f43ad96b29a666edbc7","url_list":["https://p26-sign.douyinpic.com/tos-cn-p-0015/fed0bc0035844f43ad96b29a666edbc7~noop.jpeg?x-expires=1643749200&x-signature=OoLlwI02o2csJ0T45NPkFFzQ1EU%3D&from=3218412987","https://p9-sign.douyinpic.com/tos-cn-p-0015/fed0bc0035844f43ad96b29a666edbc7~noop.jpeg?x-expires=1643749200&x-signature=wj6kvCGM5R5QeQ6YC8mIxsaIlGA%3D&from=3218412987","https://p3-sign.douyinpic.com/tos-cn-p-0015/fed0bc0035844f43ad96b29a666edbc7~noop.jpeg?x-expires=1643749200&x-signature=NluVAsRTGac3uyMLHLwRKWJej1M%3D&from=3218412987"]},"video_count":3,"sentence_tag":4003,"word_sub_board":null,"word":"广东罗定新增4例本土感染者","word_type":1,"event_time":1643721228,"drift_info":null,"label":1,"hotlist_param":"{\"version\":1}"},{"hot_value":6145588,"drift_info":null,"word":"还是北方的红包带劲啊","position":41,"sentence_id":"537320","related_words":null,"word_sub_board":null,"challenge_id":"","word_type":1,"view_count":9379000,"sentence_tag":20002,"group_id":"7058203895843755301","word_cover":{"uri":"tos-cn-p-0015/21c6c90a656043afadc728c23c14faf9","url_list":["https://p3-sign.douyinpic.com/tos-cn-p-0015/21c6c90a656043afadc728c23c14faf9~noop.jpeg?x-expires=1643749200&x-signature=Szd0JSWcacNIs5rZfsU9qp1QXv4%3D&from=3218412987","https://p26-sign.douyinpic.com/tos-cn-p-0015/21c6c90a656043afadc728c23c14faf9~noop.jpeg?x-expires=1643749200&x-signature=Y6paUn%2BJLRedH%2BTPWbfiv9TbIOU%3D&from=3218412987","https://p9-sign.douyinpic.com/tos-cn-p-0015/21c6c90a656043afadc728c23c14faf9~noop.jpeg?x-expires=1643749200&x-signature=0esvcs3HyvBYhogFai69SMtgTbo%3D&from=3218412987"]},"video_count":8,"event_time":1643673685,"hotlist_param":"{\"version\":1}","aweme_infos":null,"discuss_video_count":0,"label":1},{"challenge_id":"","sentence_tag":20002,"discuss_video_count":0,"label":1,"word_type":1,"related_words":null,"view_count":10660567,"hotlist_param":"{\"version\":1}","group_id":"7058600229470410023","video_count":4,"drift_info":null,"aweme_infos":null,"word_sub_board":null,"hot_value":6045605,"word_cover":{"uri":"tos-cn-p-0015/983f74626c3b4f7795ba7fbd1d640ac6","url_list":["https://p3-sign.douyinpic.com/tos-cn-p-0015/983f74626c3b4f7795ba7fbd1d640ac6~noop.jpeg?x-expires=1643749200&x-signature=SZkXXBUO7FLlyK3s7Q%2BjM8pgqqs%3D&from=3218412987","https://p9-sign.douyinpic.com/tos-cn-p-0015/983f74626c3b4f7795ba7fbd1d640ac6~noop.jpeg?x-expires=1643749200&x-signature=nGaVbi9OtdnraJt2Iso5LqyeZg8%3D&from=3218412987","https://p26-sign.douyinpic.com/tos-cn-p-0015/983f74626c3b4f7795ba7fbd1d640ac6~noop.jpeg?x-expires=1643749200&x-signature=XZMq%2F77QSFQMoPRs6Cx0De4HNZE%3D&from=3218412987"]},"position":42,"sentence_id":"537743","event_time":1643722414,"word":"当氛围组灯光师回村过年"},{"label":0,"word_type":1,"hotlist_param":"{\"version\":1}","aweme_infos":null,"word_sub_board":null,"hot_value":5994643,"sentence_id":"536986","event_time":1643611963,"article_detail_count":1,"group_id":"7057936268953752873","view_count":6824243,"drift_info":null,"sentence_tag":5000,"discuss_video_count":0,"can_extend_detail":false,"related_words":null,"word":"TVB群星献唱北京冬奥音乐短片","challenge_id":"","word_cover":{"uri":"tos-cn-p-0015/c9f99ef5fec64124b1dd00dd8732cfeb","url_list":["https://p9-sign.douyinpic.com/tos-cn-p-0015/c9f99ef5fec64124b1dd00dd8732cfeb~noop.jpeg?x-expires=1643749200&x-signature=98M8SK5aGfSigGL7V5Mhn255luQ%3D&from=3218412987","https://p3-sign.douyinpic.com/tos-cn-p-0015/c9f99ef5fec64124b1dd00dd8732cfeb~noop.jpeg?x-expires=1643749200&x-signature=%2Bb0BMd%2BK2kH0GuRi2IbCvN71pyM%3D&from=3218412987","https://p26-sign.douyinpic.com/tos-cn-p-0015/c9f99ef5fec64124b1dd00dd8732cfeb~noop.jpeg?x-expires=1643749200&x-signature=TeIWTu6bx%2FB1UXBqNzV8G5gNXVY%3D&from=3218412987"]},"position":43,"video_count":5},{"aweme_infos":null,"discuss_video_count":0,"article_detail_count":2,"can_extend_detail":false,"word_type":1,"event_time":1643639508,"view_count":5114296,"hotlist_param":"{\"version\":1}","challenge_id":"","position":44,"related_words":null,"sentence_tag":2006,"word_sub_board":null,"word_cover":{"uri":"tos-cn-p-0015/ceb05c8cca0645d5a0a1e4bb1c9e5af2","url_list":["https://p3-sign.douyinpic.com/tos-cn-p-0015/ceb05c8cca0645d5a0a1e4bb1c9e5af2~noop.jpeg?x-expires=1643749200&x-signature=3zhpwdyZY6xaw2zvaUwdDP3JFXo%3D&from=3218412987","https://p6-sign.douyinpic.com/tos-cn-p-0015/ceb05c8cca0645d5a0a1e4bb1c9e5af2~noop.jpeg?x-expires=1643749200&x-signature=mx7RtI1FD%2F2Y91%2B2xYXKnVymS9M%3D&from=3218412987","https://p26-sign.douyinpic.com/tos-cn-p-0015/ceb05c8cca0645d5a0a1e4bb1c9e5af2~noop.jpeg?x-expires=1643749200&x-signature=Bib6Gk4T3Zmg2UKZYnLrjRAuHY4%3D&from=3218412987"]},"group_id":"7058073824588387598","sentence_id":"537242","drift_info":null,"word":"刘涛贾乃亮被魔方整明白了","label":1,"hot_value":5880828,"video_count":4},{"word_cover":{"uri":"tos-cn-p-0015/6bbd2340d98342078ca2e762a8dbc00e_1643599021","url_list":["https://p6-sign.douyinpic.com/tos-cn-p-0015/6bbd2340d98342078ca2e762a8dbc00e_1643599021~noop.jpeg?x-expires=1643749200&x-signature=mwVdmvUkun1rBtf4t%2BWaXItOp9g%3D&from=3218412987","https://p3-sign.douyinpic.com/tos-cn-p-0015/6bbd2340d98342078ca2e762a8dbc00e_1643599021~noop.jpeg?x-expires=1643749200&x-signature=Y16%2BeIedrRfvHYbY%2FPCmBeWfOlU%3D&from=3218412987","https://p26-sign.douyinpic.com/tos-cn-p-0015/6bbd2340d98342078ca2e762a8dbc00e_1643599021~noop.jpeg?x-expires=1643749200&x-signature=tYWu5Is3aihFIQxB2SAQm8NNzfA%3D&from=3218412987"]},"position":45,"group_id":"7058215986755966221","drift_info":null,"word":"一年一度顶级拉扯大赛","label":1,"discuss_video_count":1,"event_time":1643678035,"hotlist_param":"{\"version\":1}","video_count":10,"word_type":1,"sentence_id":"537343","related_words":null,"sentence_tag":20002,"hot_value":5857143,"challenge_id":"","word_sub_board":null,"view_count":6424093,"aweme_infos":null},{"related_words":null,"aweme_infos":null,"sentence_tag":2007,"word":"明星虎年第一条抖音","word_cover":{"uri":"tos-cn-p-0015/0226dcd1494c4f5ca928e89772c26033_1643644810","url_list":["https://p9-sign.douyinpic.com/tos-cn-p-0015/0226dcd1494c4f5ca928e89772c26033_1643644810~noop.jpeg?x-expires=1643749200&x-signature=6yNQP%2F%2BV8xqc7aUNfx2u1TNGtS8%3D&from=3218412987","https://p3-sign.douyinpic.com/tos-cn-p-0015/0226dcd1494c4f5ca928e89772c26033_1643644810~noop.jpeg?x-expires=1643749200&x-signature=UXQK1JvaFjAenB8rNN9NfNFeSaw%3D&from=3218412987","https://p6-sign.douyinpic.com/tos-cn-p-0015/0226dcd1494c4f5ca928e89772c26033_1643644810~noop.jpeg?x-expires=1643749200&x-signature=cB1mwbCpVOvohOy3B99vzH2cFAQ%3D&from=3218412987"]},"group_id":"7058109588068275487","view_count":3836385,"event_time":1643648517,"hotlist_param":"{\"version\":1}","label":5,"challenge_id":"","video_count":15,"word_type":1,"discuss_video_count":0,"word_sub_board":[3],"hot_value":5849830,"position":46,"sentence_id":"537303","drift_info":null},{"video_count":140,"group_id":"6606411771538314503","word_type":1,"related_words":null,"hotlist_param":"{\"version\":1}","sentence_tag":20002,"word":"新年快乐","label":1,"event_time":1643688884,"drift_info":null,"word_sub_board":null,"position":47,"sentence_id":"537444","view_count":48158263,"discuss_video_count":0,"hot_value":5830433,"challenge_id":"","word_cover":{"uri":"tos-cn-p-0015/e6579f9d33da42e5a53ed69407939394","url_list":["https://p3-sign.douyinpic.com/tos-cn-p-0015/e6579f9d33da42e5a53ed69407939394~noop.jpeg?x-expires=1643749200&x-signature=n%2BVbspRosCmkH4mKkbu2LXwT0%2BM%3D&from=3218412987","https://p6-sign.douyinpic.com/tos-cn-p-0015/e6579f9d33da42e5a53ed69407939394~noop.jpeg?x-expires=1643749200&x-signature=jLNEL%2BCqbzeIV9%2BAgT1vQ6cYakU%3D&from=3218412987","https://p26-sign.douyinpic.com/tos-cn-p-0015/e6579f9d33da42e5a53ed69407939394~noop.jpeg?x-expires=1643749200&x-signature=80tJvO01SM77FDIlZrOwNA79j4U%3D&from=3218412987"]},"aweme_infos":null,"article_detail_count":1},{"word_sub_board":[3],"word":"家有萌虎闹新春","sentence_id":"537000","event_time":1643613288,"related_words":null,"hotlist_param":"{\"version\":1}","video_count":93,"drift_info":null,"sentence_tag":1001,"label":9,"aweme_infos":null,"word_type":1,"view_count":865082,"discuss_video_count":0,"hot_value":5803015,"challenge_id":"","word_cover":{"uri":"tos-cn-p-0015/fcae21fb66534296a7a4fa214196c457","url_list":["https://p26-sign.douyinpic.com/tos-cn-p-0015/fcae21fb66534296a7a4fa214196c457~noop.jpeg?x-expires=1643749200&x-signature=5BOp2NTeYBgMkP6Q4yvzjsVOd00%3D&from=3218412987","https://p9-sign.douyinpic.com/tos-cn-p-0015/fcae21fb66534296a7a4fa214196c457~noop.jpeg?x-expires=1643749200&x-signature=02BWyRgGRaLtfSvkY4i2sDvc%2BvU%3D&from=3218412987","https://p6-sign.douyinpic.com/tos-cn-p-0015/fcae21fb66534296a7a4fa214196c457~noop.jpeg?x-expires=1643749200&x-signature=EHAcWNUzRrIMQbXQN2AEhrvzosE%3D&from=3218412987"]},"position":48,"group_id":"7053318879938417958"},{"hotlist_param":"{\"version\":1}","word":"过年如何把亲戚整不会","challenge_id":"","event_time":1643585000,"word_type":1,"sentence_id":"536755","view_count":2469589,"drift_info":null,"aweme_infos":null,"label":1,"hot_value":5751883,"video_count":45,"discuss_video_count":0,"group_id":"7057822336162960648","word_sub_board":null,"sentence_tag":20002,"word_cover":{"uri":"tos-cn-p-0015/fe7dfcb8e2a344e183b9b0041700196d_1643550323","url_list":["https://p26-sign.douyinpic.com/tos-cn-p-0015/fe7dfcb8e2a344e183b9b0041700196d_1643550323~noop.jpeg?x-expires=1643749200&x-signature=Q%2FC3%2Fhr7FOZUH1XbrHyIaGQL%2Fb8%3D&from=3218412987","https://p3-sign.douyinpic.com/tos-cn-p-0015/fe7dfcb8e2a344e183b9b0041700196d_1643550323~noop.jpeg?x-expires=1643749200&x-signature=KtUYfMn6bPBrKKFNcXEPBwAXMx4%3D&from=3218412987","https://p6-sign.douyinpic.com/tos-cn-p-0015/fe7dfcb8e2a344e183b9b0041700196d_1643550323~noop.jpeg?x-expires=1643749200&x-signature=YZN%2F0tW55UnJwlhzGAbluZ7Q4XY%3D&from=3218412987"]},"position":49,"related_words":null},{"word_type":1,"challenge_id":"","position":50,"group_id":"7058492828096501030","video_count":4,"drift_info":null,"word":"流浪地球2上映倒计时一周年","label":3,"word_cover":{"uri":"tos-cn-p-0015/dcca1e7ed19440da8efb9ad51ad3b50c_1643647540","url_list":["https://p3-sign.douyinpic.com/tos-cn-p-0015/dcca1e7ed19440da8efb9ad51ad3b50c_1643647540~noop.jpeg?x-expires=1643749200&x-signature=26uRyHKXpbVpWE6KKZ8aaT5IENo%3D&from=3218412987","https://p9-sign.douyinpic.com/tos-cn-p-0015/dcca1e7ed19440da8efb9ad51ad3b50c_1643647540~noop.jpeg?x-expires=1643749200&x-signature=3PrSlTVyWujvF3r3R1BJd%2FBcrAs%3D&from=3218412987","https://p26-sign.douyinpic.com/tos-cn-p-0015/dcca1e7ed19440da8efb9ad51ad3b50c_1643647540~noop.jpeg?x-expires=1643749200&x-signature=QQvWR4%2FSmaX%2BNV4zRrTpZkdCKYk%3D&from=3218412987"]},"aweme_infos":null,"sentence_tag":2001,"word_sub_board":null,"hot_value":5748546,"related_words":null,"view_count":472788,"hotlist_param":"{\"version\":1}","discuss_video_count":0,"can_extend_detail":false,"sentence_id":"537543","event_time":1643699152}],"active_time":"2022-02-01 23:15:31","share_info":{"share_title":"我在看抖音热榜，发现最火的内容，赶快来看！","share_link_desc":"我在看抖音热榜，发现最火的内容，赶快来看！戳这里>>","share_url":"https://www.iesdouyin.com/share/billboard/?id=0"},"trending_list":[{"discuss_video_count":0,"hot_value":0,"word_type":3,"sentence_tag":2001,"drift_info":null,"aweme_infos":null,"word_sub_board":null,"article_detail_count":2,"word":"看这个杀手不太冷静笑不停了","event_time":1643691326,"related_words":null,"sentence_id":"537462","group_id":"7058078357304530212","hotlist_param":"{\"version\":1}","label":5,"word_cover":{"uri":"tos-cn-p-0015/06bf6cf7285e49b5b3a6fd068bfc6fec","url_list":["https://p9-sign.douyinpic.com/tos-cn-p-0015/06bf6cf7285e49b5b3a6fd068bfc6fec~noop.jpeg?x-expires=1643749200&x-signature=DnQlg0agIqMxnd%2BCW4O9yygTCW4%3D&from=3218412987","https://p26-sign.douyinpic.com/tos-cn-p-0015/06bf6cf7285e49b5b3a6fd068bfc6fec~noop.jpeg?x-expires=1643749200&x-signature=jw9hInvSpr43aaQarZwtVq3HmiU%3D&from=3218412987","https://p3-sign.douyinpic.com/tos-cn-p-0015/06bf6cf7285e49b5b3a6fd068bfc6fec~noop.jpeg?x-expires=1643749200&x-signature=ezDZUDmnyhtXCviM23sarxsCucY%3D&from=3218412987"]},"video_count":23},{"label":0,"video_count":2,"related_words":null,"hotlist_param":"{\"version\":1}","aweme_infos":null,"word":"被徐志胜回家过年的气质拿捏了","event_time":1643686982,"drift_info":null,"hot_value":0,"word_type":3,"word_cover":{"uri":"tos-cn-p-0015/ca50f046922e4b4db2818e18070365b4","url_list":["https://p26-sign.douyinpic.com/tos-cn-p-0015/ca50f046922e4b4db2818e18070365b4~noop.jpeg?x-expires=1643749200&x-signature=NKDVa8IElCJS6e17ZBRFAZYhXvo%3D&from=3218412987","https://p9-sign.douyinpic.com/tos-cn-p-0015/ca50f046922e4b4db2818e18070365b4~noop.jpeg?x-expires=1643749200&x-signature=Rejm31NgMRNMF9w%2FL3AfSMYvNgI%3D&from=3218412987","https://p3-sign.douyinpic.com/tos-cn-p-0015/ca50f046922e4b4db2818e18070365b4~noop.jpeg?x-expires=1643749200&x-signature=FE%2B0XB4qx7MFltrvTE3jyrN5sTw%3D&from=3218412987"]},"group_id":"7058194318041208072","sentence_id":"537424","sentence_tag":2012,"word_sub_board":null},{"word":"广东惠州报告1例确诊病例","event_time":1643704281,"video_count":3,"group_id":"7058511159427618087","sentence_id":"537584","related_words":null,"hotlist_param":"{\"version\":1}","aweme_infos":null,"word_sub_board":null,"article_detail_count":8,"label":0,"hot_value":0,"word_cover":{"uri":"tos-cn-p-0015/cea3754798aa46b982070edb440a1ee8_1643704103","url_list":["https://p3-sign.douyinpic.com/tos-cn-p-0015/cea3754798aa46b982070edb440a1ee8_1643704103~noop.jpeg?x-expires=1643749200&x-signature=yiGiNYdBZy9I1omqdCZ2OblzwxE%3D&from=3218412987","https://p9-sign.douyinpic.com/tos-cn-p-0015/cea3754798aa46b982070edb440a1ee8_1643704103~noop.jpeg?x-expires=1643749200&x-signature=r0v5XriUa0aoFI0ganjwk8mRA9Q%3D&from=3218412987","https://p26-sign.douyinpic.com/tos-cn-p-0015/cea3754798aa46b982070edb440a1ee8_1643704103~noop.jpeg?x-expires=1643749200&x-signature=dtK%2FOowMxEyekZweXbzadpEWeDU%3D&from=3218412987"]},"word_type":3,"drift_info":null,"sentence_tag":4003,"discuss_video_count":0},{"hot_value":0,"sentence_id":"536713","drift_info":null,"hotlist_param":"{\"version\":1}","article_detail_count":1,"event_time":1643556451,"aweme_infos":null,"word_type":3,"related_words":null,"sentence_tag":2006,"word":"被德云社的开场秀电到了","label":0,"word_cover":{"uri":"tos-cn-p-0015/8c847d2c31d442ddaa61b7f228a019d2_1643543822","url_list":["https://p26-sign.douyinpic.com/tos-cn-p-0015/8c847d2c31d442ddaa61b7f228a019d2_1643543822~noop.jpeg?x-expires=1643749200&x-signature=LazzT4rr6A3Ybwp5wZxswllkmVI%3D&from=3218412987","https://p3-sign.douyinpic.com/tos-cn-p-0015/8c847d2c31d442ddaa61b7f228a019d2_1643543822~noop.jpeg?x-expires=1643749200&x-signature=pjLgju%2FFOfJ%2B3W%2BfME9EnAXkKLo%3D&from=3218412987","https://p9-sign.douyinpic.com/tos-cn-p-0015/8c847d2c31d442ddaa61b7f228a019d2_1643543822~noop.jpeg?x-expires=1643749200&x-signature=O2ZVQlLmLpzC2KkbIoVzWTem0WM%3D&from=3218412987"]},"video_count":4,"group_id":"7058779499895772448","discuss_video_count":0,"word_sub_board":null},{"word":"张小斐大衣","word_cover":{"url_list":["https://p26-sign.douyinpic.com/tos-cn-p-0015/a4a97aa3686c49c5a57ad83074e4ff9b_1643636375~noop.jpeg?x-expires=1643749200&x-signature=aQLdRpWnEKXsODxWcQ7dSeZxgJo%3D&from=3218412987","https://p6-sign.douyinpic.com/tos-cn-p-0015/a4a97aa3686c49c5a57ad83074e4ff9b_1643636375~noop.jpeg?x-expires=1643749200&x-signature=YLY2eXiYl8tk5yguug%2BZ4JVvJmU%3D&from=3218412987","https://p3-sign.douyinpic.com/tos-cn-p-0015/a4a97aa3686c49c5a57ad83074e4ff9b_1643636375~noop.jpeg?x-expires=1643749200&x-signature=BLDVtN2Bz6zMYdRNfPKuqL2zzx4%3D&from=3218412987"],"uri":"tos-cn-p-0015/a4a97aa3686c49c5a57ad83074e4ff9b_1643636375"},"word_type":3,"event_time":1643637581,"article_detail_count":1,"video_count":11,"sentence_id":"537232","related_words":null,"aweme_infos":null,"sentence_tag":2006,"group_id":"6579762059875980552","hotlist_param":"{\"version\":1}","discuss_video_count":0,"label":5,"hot_value":0,"drift_info":null,"word_sub_board":null}],"trending_desc":"实时上升热点"},"ad_search_list":null,"banner_dark":{"uri":"32e5200049fac86168117","url_list":["https://p3-sign.douyinpic.com/obj/32e5200049fac86168117?x-expires=1643749200&x-signature=CoveJGFjQMFaj2FCiVs1nTGYA0s%3D&from=65706370"]},"banner_light":{"url_list":["https://p3-sign.douyinpic.com/obj/321f4000f703369c24604?x-expires=1643749200&x-signature=KznaF1LLhIxgWPAv2EZZuhpxnvw%3D&from=65706370"],"uri":"321f4000f703369c24604"},"board_tabs":null,"extra":{"now":1643728554000,"fatal_item_ids":[],"logid":"2022020123155301021207714908D7D883"},"log_pb":{"impr_id":"2022020123155301021207714908D7D883"}}
